fp/__init__.py
fp/list.py
fp/monoid.py
fp/option.py
fp/sequence.py
fp/validation.py
python_fp-0.2.dist-info/METADATA
python_fp-0.2.dist-info/RECORD
python_fp-0.2.dist-info/WHEEL
python_fp-0.2.dist-info/top_level.txt
