Metadata-Version: 2.1
Name: python-fp
Version: 0.2
Summary: Libraries for adding collections and fp concepts to Python
Home-page: https://github.com/dnvriend/python-fp
Author: Dennis Vriend
Author-email: dnvriend@gmail.com
License: Apache 2.0
Platform: UNKNOWN
